setup.py
src/m_car_api/__init__.py
src/m_car_api/api.py
src/m_car_api/const.py
src/m_car_api/geo.py
src/m_car_api/objects.py
src/m_car_api/objects_pydantic_1.py
src/m_car_api/objects_pydantic_2.py
src/m_car_api.egg-info/PKG-INFO
src/m_car_api.egg-info/SOURCES.txt
src/m_car_api.egg-info/dependency_links.txt
src/m_car_api.egg-info/namespace_packages.txt
src/m_car_api.egg-info/not-zip-safe
src/m_car_api.egg-info/requires.txt
src/m_car_api.egg-info/top_level.txt
src/m_car_api/test/test_miles_api.py
src/m_car_api/test/test_objects.py