Metadata-Version: 2.1
Name: m_car_api
Version: 1.2.0
Home-page: https://github.com/cbrand/m_car_api
Author: Christoph Brand
Author-email: christoph@brand.rest
License: MIT
Project-URL: GitHub, https://github.com/cbrand/m_car_api
Classifier: Development Status :: 5 - Production/Stable
Classifier: Intended Audience :: Developers
Classifier: Operating System :: OS Independent
Classifier: Programming Language :: Python
Classifier: Programming Language :: Python :: 3
Classifier: Programming Language :: Python :: 3.10
Classifier: Programming Language :: Python :: 3.11
Classifier: Programming Language :: Python :: 3.12
Classifier: Programming Language :: Python :: 3 :: Only
Classifier: Topic :: Software Development :: Libraries :: Python Modules
Requires-Python: >=3.10
Requires-Dist: requests
Requires-Dist: mujson
Requires-Dist: pydantic
Provides-Extra: test
Requires-Dist: black>=19.10b0; extra == "test"
Requires-Dist: coverage<7,>=5.1; extra == "test"
Requires-Dist: faker<19,>=18; extra == "test"
Requires-Dist: flake8<6,>=5.0.4; extra == "test"
Requires-Dist: mypy>=0.961; extra == "test"
Requires-Dist: pre-commit<4,>=3; extra == "test"
Requires-Dist: pytest-cases<4,>=3.1.1; extra == "test"
Requires-Dist: pytest-html; extra == "test"
Requires-Dist: pytest<8,>=7; extra == "test"
Requires-Dist: pytest-mock<4,>=3.5.1; extra == "test"
Requires-Dist: python-dotenv<2,>=1; extra == "test"
Requires-Dist: python-semantic-release<9,>=8; extra == "test"
Requires-Dist: twine<4,>=3.1.1; extra == "test"
Provides-Extra: pydantic-1
Requires-Dist: pydantic<2,>=1; extra == "pydantic-1"
Requires-Dist: pydantic_computed; extra == "pydantic-1"
Provides-Extra: pydantic-2
Requires-Dist: pydantic<3,>=2; extra == "pydantic-2"
Provides-Extra: pyproj
Requires-Dist: pyproj; extra == "pyproj"
